odoo/addons/stock_picking_to_batch_group_fields/README.rst
odoo/addons/stock_picking_to_batch_group_fields/__init__.py
odoo/addons/stock_picking_to_batch_group_fields/__manifest__.py
odoo/addons/stock_picking_to_batch_group_fields/i18n/es.po
odoo/addons/stock_picking_to_batch_group_fields/i18n/it.po
odoo/addons/stock_picking_to_batch_group_fields/i18n/stock_picking_to_batch_group_fields.pot
odoo/addons/stock_picking_to_batch_group_fields/readme/CONFIGURE.md
odoo/addons/stock_picking_to_batch_group_fields/readme/CONTEXT.md
odoo/addons/stock_picking_to_batch_group_fields/readme/CONTRIBUTORS.md
odoo/addons/stock_picking_to_batch_group_fields/readme/DESCRIPTION.md
odoo/addons/stock_picking_to_batch_group_fields/readme/USAGE.md
odoo/addons/stock_picking_to_batch_group_fields/security/ir.model.access.csv
odoo/addons/stock_picking_to_batch_group_fields/static/description/icon.png
odoo/addons/stock_picking_to_batch_group_fields/static/description/index.html
odoo/addons/stock_picking_to_batch_group_fields/tests/__init__.py
odoo/addons/stock_picking_to_batch_group_fields/tests/test_batch_group_field.py
odoo/addons/stock_picking_to_batch_group_fields/wizard/__init__.py
odoo/addons/stock_picking_to_batch_group_fields/wizard/stock_picking_to_batch.py
odoo/addons/stock_picking_to_batch_group_fields/wizard/stock_picking_to_batch_views.xml
odoo_addon_stock_picking_to_batch_group_fields-18.0.1.0.2.dist-info/METADATA
odoo_addon_stock_picking_to_batch_group_fields-18.0.1.0.2.dist-info/WHEEL
odoo_addon_stock_picking_to_batch_group_fields-18.0.1.0.2.dist-info/top_level.txt
odoo_addon_stock_picking_to_batch_group_fields-18.0.1.0.2.dist-info/RECORD
